yarrow/__init__.py
yarrow/bipartite_multigraph.py
yarrow/cupy.py
yarrow/diagram.py
yarrow/finite_function.py
yarrow/array/__init__.py
yarrow/array/cupy.py
yarrow/array/numpy.py
yarrow/decompose/frobenius.py
yarrow/functor/__init__.py
yarrow/functor/functor.py
yarrow/functor/optic.py
yarrow/numpy/__init__.py
yarrow/numpy/layer.py
yarrow/segmented/__init__.py
yarrow/segmented/finite_function.py
yarrow/segmented/operations.py
yarrow_diagrams-0.0.3.1.dist-info/METADATA
yarrow_diagrams-0.0.3.1.dist-info/WHEEL
yarrow_diagrams-0.0.3.1.dist-info/licenses/LICENSE
yarrow_diagrams-0.0.3.1.dist-info/RECORD
