Metadata-Version: 2.1
Name: yarrow-diagrams
Version: 0.0.3.1
Summary: yarrow diagrams
Project-URL: Homepage, https://yarrow.id
Project-URL: Github, https://github.com/yarrow-id/diagrams/
Project-URL: Documentation, https://yarrow-diagrams.readthedocs.io/
Author-email: Paul Wilson <paul@statusfailed.com>
License-File: LICENSE
Classifier: License :: OSI Approved :: MIT License
Classifier: Programming Language :: Python :: 3
Requires-Python: >=3.7
Requires-Dist: numpy~=1.23.3
Requires-Dist: scipy~=1.10.0
